UnextPythonServiceUtils/__init__.py
UnextPythonServiceUtils/clients/__init__.py
UnextPythonServiceUtils/clients/http_client.py
UnextPythonServiceUtils/clients/bedrock_client/__init__.py
UnextPythonServiceUtils/clients/bedrock_client/base_llm_operation.py
UnextPythonServiceUtils/clients/bedrock_client/bedrock_client.py
UnextPythonServiceUtils/clients/bedrock_client/call_bedrock.py
UnextPythonServiceUtils/clients/bedrock_client/fm_config.py
UnextPythonServiceUtils/clients/bedrock_client/foundation_models.py
UnextPythonServiceUtils/clients/bedrock_client/local_interfaces_typehinter.py
UnextPythonServiceUtils/clients/redis_client/__init__.py
UnextPythonServiceUtils/clients/redis_client/async_redisclient.py
UnextPythonServiceUtils/clients/redis_client/enums.py
UnextPythonServiceUtils/clients/redis_client/sync_redisclient.py
UnextPythonServiceUtils/clients/sqs_client/__init__.py
UnextPythonServiceUtils/clients/sqs_client/helpers.py
UnextPythonServiceUtils/clients/sqs_client/initiator.py
UnextPythonServiceUtils/clients/sqs_client/message_handler.py
UnextPythonServiceUtils/clients/sqs_client/polling.py
UnextPythonServiceUtils/clients/sqs_client/post_message.py
UnextPythonServiceUtils/clients/sqs_client/queue_config.py
UnextPythonServiceUtils/context/__init__.py
UnextPythonServiceUtils/context/vars.py
UnextPythonServiceUtils/guards/__init__.py
UnextPythonServiceUtils/guards/rate_limiter_guard.py
UnextPythonServiceUtils/interfaces/__init__.py
UnextPythonServiceUtils/interfaces/interfaces_pd.py
UnextPythonServiceUtils/interfaces/interfaces_th.py
UnextPythonServiceUtils/ioc/__init__.py
UnextPythonServiceUtils/ioc/singleton.py
UnextPythonServiceUtils/logging/__init__.py
UnextPythonServiceUtils/logging/base_logger.py
UnextPythonServiceUtils/logging/logger_decorator.py
UnextPythonServiceUtils/messaging_utils/__init__.py
UnextPythonServiceUtils/messaging_utils/async_task_handler.py
UnextPythonServiceUtils/middlewares/__init__.py
unextpythonserviceutils-0.1.15.dist-info/LICENSE
unextpythonserviceutils-0.1.15.dist-info/METADATA
unextpythonserviceutils-0.1.15.dist-info/WHEEL
unextpythonserviceutils-0.1.15.dist-info/top_level.txt
unextpythonserviceutils-0.1.15.dist-info/RECORD
